odoo/addons/hr_expense_journal/README.rst
odoo/addons/hr_expense_journal/__init__.py
odoo/addons/hr_expense_journal/__manifest__.py
odoo/addons/hr_expense_journal/i18n/es.po
odoo/addons/hr_expense_journal/i18n/hr_expense_journal.pot
odoo/addons/hr_expense_journal/i18n/it.po
odoo/addons/hr_expense_journal/models/__init__.py
odoo/addons/hr_expense_journal/models/hr_expense.py
odoo/addons/hr_expense_journal/readme/CONTRIBUTORS.rst
odoo/addons/hr_expense_journal/readme/DESCRIPTION.rst
odoo/addons/hr_expense_journal/readme/USAGE.rst
odoo/addons/hr_expense_journal/static/description/icon.png
odoo/addons/hr_expense_journal/static/description/index.html
odoo/addons/hr_expense_journal/views/hr_expense_views.xml
odoo14_addon_hr_expense_journal-14.0.1.0.1.dev8.dist-info/METADATA
odoo14_addon_hr_expense_journal-14.0.1.0.1.dev8.dist-info/WHEEL
odoo14_addon_hr_expense_journal-14.0.1.0.1.dev8.dist-info/top_level.txt
odoo14_addon_hr_expense_journal-14.0.1.0.1.dev8.dist-info/RECORD
